pandas_dash/__init__.py
pandas_dash/dash_accessor.py
pandas_dash/formatting.py
pandas_dash-0.1.3.dist-info/LICENSE.md
pandas_dash-0.1.3.dist-info/METADATA
pandas_dash-0.1.3.dist-info/WHEEL
pandas_dash-0.1.3.dist-info/RECORD
