Metadata-Version: 2.1
Name: pandas-dash
Version: 0.1.3
Summary: Tools for working with Pandas, Plotly, and Dash.
Home-page: https://github.com/lucasjamar/pandas-dash
License: Apache-2.0
Author: lucas.jamar
Author-email: lucasjamar@hotmail.com
Requires-Python: >=3.8
Classifier: License :: OSI Approved :: Apache Software License
Classifier: Programming Language :: Python :: 3
Classifier: Programming Language :: Python :: 3.8
Classifier: Programming Language :: Python :: 3.9
Classifier: Programming Language :: Python :: 3.10
Classifier: Programming Language :: Python :: 3.11
Classifier: Programming Language :: Python :: 3.12
Requires-Dist: dash (>=2,<3)
Requires-Dist: pandas (>=2.0.0)
Project-URL: Repository, https://github.com/lucasjamar/pandas-dash
